pyswap/__init__.py
pyswap/log.py
pyswap/components/__init__.py
pyswap/components/boundary.py
pyswap/components/crop.py
pyswap/components/drainage.py
pyswap/components/irrigation.py
pyswap/components/metadata.py
pyswap/components/meteorology.py
pyswap/components/simsettings.py
pyswap/components/soilwater.py
pyswap/components/tables.py
pyswap/components/transport.py
pyswap/core/__init__.py
pyswap/core/basemodel.py
pyswap/core/defaults.py
pyswap/core/fields.py
pyswap/core/parsers.py
pyswap/core/serializers.py
pyswap/core/validation.yaml
pyswap/core/valueranges.py
pyswap/core/cli/__init__.py
pyswap/core/cli/cli.py
pyswap/core/cli/templates/README
pyswap/core/cli/templates/README_template
pyswap/core/cli/templates/basic_template.py
pyswap/core/cli/templates/crop_tables_template.yaml
pyswap/core/cli/templates/notebook.json
pyswap/core/cli/templates/notebook_full.json
pyswap/core/cli/templates/pixi.toml
pyswap/core/cli/templates/pixi_instructions.md
pyswap/core/cli/templates/script.txt
pyswap/core/io/__init__.py
pyswap/core/io/io_ascii.py
pyswap/core/io/io_csv.py
pyswap/core/io/io_yaml.py
pyswap/core/io/process_ascii.py
pyswap/core/io/processors.py
pyswap/core/plot/__init__.py
pyswap/core/plot/evapotranspiration.py
pyswap/core/plot/watercontent.py
pyswap/db/__init__.py
pyswap/db/co2concentration.py
pyswap/db/cropdb.py
pyswap/db/hdf5.py
pyswap/gis/__init__.py
pyswap/gis/location.py
pyswap/libs/__init__.py
pyswap/libs/WOFOST_crop_parameters/README.rst
pyswap/libs/WOFOST_crop_parameters/barley.yaml
pyswap/libs/WOFOST_crop_parameters/cassava.yaml
pyswap/libs/WOFOST_crop_parameters/changelog.txt
pyswap/libs/WOFOST_crop_parameters/chickpea.yaml
pyswap/libs/WOFOST_crop_parameters/cotton.yaml
pyswap/libs/WOFOST_crop_parameters/cowpea.yaml
pyswap/libs/WOFOST_crop_parameters/crops.yaml
pyswap/libs/WOFOST_crop_parameters/fababean.yaml
pyswap/libs/WOFOST_crop_parameters/groundnut.yaml
pyswap/libs/WOFOST_crop_parameters/maize.yaml
pyswap/libs/WOFOST_crop_parameters/millet.yaml
pyswap-0.3.9.dist-info/licenses/LICENSE
pyswap-0.3.9.dist-info/METADATA
pyswap-0.3.9.dist-info/WHEEL
pyswap-0.3.9.dist-info/entry_points.txt
pyswap-0.3.9.dist-info/top_level.txt
pyswap-0.3.9.dist-info/RECORD
