Metadata-Version: 2.4
Name: pyswap
Version: 0.3.9
Summary: Python wrapper for SWAP hydrological model.
Author-email: Mateusz <zawadzkimat@outlook.com>
License-Expression: MIT
Project-URL: Repository, https://github.com/zawadzkim/pyswap
Project-URL: Documentation, https://zawadzkim.github.io/pyswap/
Requires-Python: >=3.11
License-File: LICENSE
Requires-Dist: pandas<3,>=2.0
Requires-Dist: numpy<3,>=1.26
Requires-Dist: chardet<6,>=5.0
Requires-Dist: h5py<4,>=3.10
Requires-Dist: shapely<3,>=2.0
Requires-Dist: pyproj<4,>=3.6
Requires-Dist: pydantic<3,>=2.0
Requires-Dist: pandera[strategies]<1,>=0.20
Requires-Dist: matplotlib<4,>=3.8
Requires-Dist: typer<1,>=0.9
Requires-Dist: seaborn<1,>=0.13
Requires-Dist: pyyaml<7,>=6.0
Requires-Dist: knmi-py<0.3,>=0.2.0
Provides-Extra: test
Requires-Dist: pytest>=8.2.2; extra == "test"
Requires-Dist: pytest-cov>=5.0.0; extra == "test"
Requires-Dist: jupyter; extra == "test"
Provides-Extra: dev
Requires-Dist: pytest>=8.2.2; extra == "dev"
Requires-Dist: pytest-cov>=5.0.0; extra == "dev"
Requires-Dist: mypy>=1.11.0; extra == "dev"
Requires-Dist: nbstripout>=0.7.1; extra == "dev"
Requires-Dist: pre-commit>=3.8.0; extra == "dev"
Requires-Dist: ruff>=0.7.4; extra == "dev"
Requires-Dist: deptry>=0.16.2; extra == "dev"
Requires-Dist: types-pyyaml>=6.0.12; extra == "dev"
Requires-Dist: pandas-stubs>=2.2.3; extra == "dev"
Requires-Dist: h5py-stubs>=0.1.1; extra == "dev"
Requires-Dist: build; extra == "dev"
Requires-Dist: twine; extra == "dev"
Requires-Dist: jupyter; extra == "dev"
Provides-Extra: docs
Requires-Dist: mkdocs-material>=9.7.0; extra == "docs"
Requires-Dist: mkdocs-jupyter; extra == "docs"
Requires-Dist: mkdocs-include-markdown-plugin>=6.2.0; extra == "docs"
Requires-Dist: mkdocs-autorefs>=1.0.1; extra == "docs"
Requires-Dist: mkdocstrings-python>=1.10.3; extra == "docs"
Requires-Dist: mkdocs-awesome-pages-plugin>=2.10.1; extra == "docs"
Requires-Dist: mkdocs-exclude-search>=0.6.6; extra == "docs"
Dynamic: license-file
